finder_enrichment_ai_client/__init__.py
finder_enrichment_ai_client/finder_enrichment_google_ai_client.py
finder_enrichment_ai_client/schemas.py
finder_enrichment_ai_client-0.2.1.dist-info/METADATA
finder_enrichment_ai_client-0.2.1.dist-info/WHEEL
finder_enrichment_ai_client-0.2.1.dist-info/top_level.txt
finder_enrichment_ai_client-0.2.1.dist-info/RECORD
