Metadata-Version: 2.4
Name: finder-enrichment-ai-client
Version: 0.2.1
Summary: Lightweight AI client package for managing API calls to various AI providers
Project-URL: Homepage, https://github.com/giacomokavanagh/finder-enrichment-orchestrator
Project-URL: Bug Tracker, https://github.com/giacomokavanagh/finder-enrichment-orchestrator/issues
Classifier: Development Status :: 3 - Alpha
Classifier: Intended Audience :: Developers
Classifier: License :: OSI Approved :: MIT License
Classifier: Programming Language :: Python :: 3
Classifier: Programming Language :: Python :: 3.8
Classifier: Programming Language :: Python :: 3.9
Classifier: Programming Language :: Python :: 3.10
Classifier: Programming Language :: Python :: 3.11
Classifier: Programming Language :: Python :: 3.12
Classifier: Topic :: Software Development :: Libraries :: Python Modules
Classifier: Topic :: Scientific/Engineering :: Artificial Intelligence
Requires-Python: >=3.8
Requires-Dist: requests>=2.25.0
Provides-Extra: dev
Requires-Dist: pytest>=7.0; extra == "dev"
Requires-Dist: pytest-cov>=4.0; extra == "dev"
Requires-Dist: black>=22.0; extra == "dev"
Requires-Dist: isort>=5.0; extra == "dev"
Requires-Dist: flake8>=5.0; extra == "dev"
Requires-Dist: mypy>=1.0; extra == "dev"
Provides-Extra: build
Requires-Dist: build>=1.0.3; extra == "build"
Requires-Dist: twine>=6.1.0; extra == "build"
